memaccess/__init__.py
memaccess-0.2.dist-info/DESCRIPTION.rst
memaccess-0.2.dist-info/METADATA
memaccess-0.2.dist-info/RECORD
memaccess-0.2.dist-info/WHEEL
memaccess-0.2.dist-info/metadata.json
memaccess-0.2.dist-info/top_level.txt
tests/__init__.py
tests/test_MemoryView.py
tests/native/__init__.py
