Metadata-Version: 2.0
Name: memaccess
Version: 0.2
Summary: Python library for Windows giving live access to a program's memory
Home-page: https://github.com/Makman2/memaccess
Author: Mischa Krüger (Makman2)
Author-email: makmanx64@gmail.com
License: MIT
Platform: UNKNOWN
